neuralpiano/README.md
neuralpiano/__init__.py
neuralpiano/bass.py
neuralpiano/denoise.py
neuralpiano/enhancer.py
neuralpiano/master.py
neuralpiano/mixer.py
neuralpiano/neuralpiano.py
neuralpiano/sample_midis.py
neuralpiano/artwork/Neural-Piano-Artwork.png
neuralpiano/artwork/Neural-Piano-Logo.png
neuralpiano/artwork/Neural-Piano-Sign.png
neuralpiano/artwork/Project-Los-Angeles.png
neuralpiano/artwork/README.md
neuralpiano/artwork/Tegridy-Code-2025.png
neuralpiano/artwork/__init__.py
neuralpiano/music2latent/README.md
neuralpiano/music2latent/__init__.py
neuralpiano/music2latent/audio.py
neuralpiano/music2latent/hparams.py
neuralpiano/music2latent/hparams_inference.py
neuralpiano/music2latent/inference.py
neuralpiano/music2latent/models.py
neuralpiano/music2latent/utils.py
neuralpiano/output_samples/README.md
neuralpiano/output_samples/__init__.py
neuralpiano/seed_midis/README.md
neuralpiano/seed_midis/__init__.py
neuralpiano/seed_midis/neural_piano_seed_midi_1.mid
neuralpiano/seed_midis/neural_piano_seed_midi_2.mid
neuralpiano/seed_midis/neural_piano_seed_midi_3.mid
neuralpiano/seed_midis/neural_piano_seed_midi_4.mid
neuralpiano/seed_midis/neural_piano_seed_midi_5.mid
neuralpiano/seed_midis/neural_piano_seed_midi_6.mid
neuralpiano-25.11.41.dist-info/licenses/LICENSE
neuralpiano-25.11.41.dist-info/METADATA
neuralpiano-25.11.41.dist-info/WHEEL
neuralpiano-25.11.41.dist-info/top_level.txt
neuralpiano-25.11.41.dist-info/RECORD
