Metadata-Version: 2.4
Name: neuralpiano
Version: 25.11.41
Summary: Hi-Fi neural MIDI piano synthesizer and MIDI renderer
Author-email: Alex Lev <alexlev61@proton.me>
Maintainer-email: Alex Lev <alexlev61@proton.me>
License-Expression: Apache-2.0
Project-URL: Homepage, https://github.com/asigalov61/neuralpiano
Project-URL: SoundCloud, https://soundcloud.com/aleksandr-sigalov-61/
Project-URL: Samples, https://soundcloud.com/aleksandr-sigalov-61/sets/neural-piano
Project-URL: Documentation, https://github.com/asigalov61/neuralpiano
Project-URL: Issues, https://github.com/asigalov61/neuralpiano/issues
Project-URL: Discussions, https://github.com/asigalov61/neuralpiano/discussions
Project-URL: Dataset, https://magenta.withgoogle.com/datasets/maestro
Keywords: MIDI,music,music ai,MIDI piano,Piano synthesizer,renderer,MIDI synthesizer,MIDI renderer,neural synthesizer,artificial intelligence,AI,audio synthesis
Classifier: Development Status :: 5 - Production/Stable
Classifier: Intended Audience :: Science/Research
Classifier: Topic :: Multimedia :: Sound/Audio :: MIDI
Classifier: Operating System :: OS Independent
Classifier: Programming Language :: Python :: 3.8
Classifier: Programming Language :: Python :: 3.9
Classifier: Programming Language :: Python :: 3.10
Classifier: Programming Language :: Python :: 3.11
Classifier: Programming Language :: Python :: 3.12
Requires-Python: >=3.8
License-File: LICENSE
Requires-Dist: tqdm
Requires-Dist: ipywidgets
Requires-Dist: matplotlib
Requires-Dist: hf-transfer
Requires-Dist: huggingface_hub
Requires-Dist: soundfile
Requires-Dist: torch
Requires-Dist: numpy==1.26.4
Requires-Dist: librosa
Requires-Dist: midirenderer
Dynamic: license-file
